setup.py
gauss_binom_distributions/Binomialdistribution.py
gauss_binom_distributions/Gaussiandistribution.py
gauss_binom_distributions/Generaldistribution.py
gauss_binom_distributions/__init__.py
gauss_binom_distributions.egg-info/PKG-INFO
gauss_binom_distributions.egg-info/SOURCES.txt
gauss_binom_distributions.egg-info/dependency_links.txt
gauss_binom_distributions.egg-info/not-zip-safe
gauss_binom_distributions.egg-info/top_level.txt