Metadata-Version: 1.0
Name: gauss-binom-distributions
Version: 1.1
Summary: Gaussian and Binomial distributions
Home-page: UNKNOWN
Author: Jan Rasmus Platou
Author-email: jrplatou@gmail.com
License: UNKNOWN
Platform: UNKNOWN
